boyaa_seed-0.1.6.data/data/3rdpartylicenses.txt
boyaa_seed-0.1.6.data/data/LICENSE.txt
boyaa_seed-0.1.6.data/data/OpenSans-Bold.ttf
boyaa_seed-0.1.6.data/data/OpenSans-BoldItalic.ttf
boyaa_seed-0.1.6.data/data/OpenSans-ExtraBold.ttf
boyaa_seed-0.1.6.data/data/OpenSans-ExtraBoldItalic.ttf
boyaa_seed-0.1.6.data/data/OpenSans-Italic.ttf
boyaa_seed-0.1.6.data/data/OpenSans-Light.ttf
boyaa_seed-0.1.6.data/data/OpenSans-LightItalic.ttf
boyaa_seed-0.1.6.data/data/OpenSans-Regular.629a55a7e793da068dc5.ttf
boyaa_seed-0.1.6.data/data/OpenSans-Regular.ttf
boyaa_seed-0.1.6.data/data/OpenSans-Semibold.ttf
boyaa_seed-0.1.6.data/data/OpenSans-SemiboldItalic.ttf
boyaa_seed-0.1.6.data/data/arrow.png
boyaa_seed-0.1.6.data/data/avatar.jpg
boyaa_seed-0.1.6.data/data/bgt.jpg
boyaa_seed-0.1.6.data/data/bowser.min.js
boyaa_seed-0.1.6.data/data/bt.jpg
boyaa_seed-0.1.6.data/data/businessIcon.png
boyaa_seed-0.1.6.data/data/businessNo.png
boyaa_seed-0.1.6.data/data/cloudPlane.png
boyaa_seed-0.1.6.data/data/compConfig.js
boyaa_seed-0.1.6.data/data/config.yaml.default
boyaa_seed-0.1.6.data/data/dbqst.jpg
boyaa_seed-0.1.6.data/data/dbt.jpg
boyaa_seed-0.1.6.data/data/drq.jpg
boyaa_seed-0.1.6.data/data/favicon.ico
boyaa_seed-0.1.6.data/data/fontawesome-webfont.674f50d287a8c48dc19b.eot
boyaa_seed-0.1.6.data/data/fontawesome-webfont.912ec66d7572ff821749.svg
boyaa_seed-0.1.6.data/data/fontawesome-webfont.af7ae505a9eed503f8b8.woff2
boyaa_seed-0.1.6.data/data/fontawesome-webfont.b06871f281fee6b241d6.ttf
boyaa_seed-0.1.6.data/data/fontawesome-webfont.fee66e712a8a08eef580.woff
boyaa_seed-0.1.6.data/data/giphy1.gif
boyaa_seed-0.1.6.data/data/index.html
boyaa_seed-0.1.6.data/data/inline.53cde9437fbfbab6a245.bundle.js
boyaa_seed-0.1.6.data/data/jquery.min.js
boyaa_seed-0.1.6.data/data/ldt.jpg
boyaa_seed-0.1.6.data/data/line.567f57385ea3dde2c9ae.gif
boyaa_seed-0.1.6.data/data/line.gif
boyaa_seed-0.1.6.data/data/loading-bars.0e7c657c2cbc1629a789.svg
boyaa_seed-0.1.6.data/data/loading-bars.svg
boyaa_seed-0.1.6.dist-info/LICENSE
boyaa_seed-0.1.6.dist-info/METADATA
boyaa_seed-0.1.6.dist-info/WHEEL
boyaa_seed-0.1.6.dist-info/entry_points.txt
boyaa_seed-0.1.6.dist-info/top_level.txt
boyaa_seed-0.1.6.dist-info/RECORD
