Metadata-Version: 2.1
Name: boyaa-seed
Version: 0.1.6
Summary: seed data report system
Home-page: http://seed.boyaa.com
License: UNKNOWN
Platform: UNKNOWN
Classifier: Programming Language :: Python :: 3
Classifier: License :: OSI Approved :: Mozilla Public License 2.0 (MPL 2.0)
Classifier: Operating System :: OS Independent
Requires-Dist: alembic (==1.0.0)
Requires-Dist: asn1crypto (==0.24.0)
Requires-Dist: astroid (==2.0.1)
Requires-Dist: certifi (==2018.8.24)
Requires-Dist: cffi (==1.11.5)
Requires-Dist: chardet (==3.0.4)
Requires-Dist: click (==6.7)
Requires-Dist: colorama (==0.3.9)
Requires-Dist: cryptography (==2.3)
Requires-Dist: decorator (==4.3.0)
Requires-Dist: flake8 (==3.5.0)
Requires-Dist: Flask (==1.0.2)
Requires-Dist: Flask-Cors (==3.0.6)
Requires-Dist: flask-marshmallow (==0.9.0)
Requires-Dist: Flask-Migrate (==2.2.1)
Requires-Dist: Flask-Script (==2.0.6)
Requires-Dist: Flask-SQLAlchemy (==2.3.2)
Requires-Dist: idna (==2.7)
Requires-Dist: infinity (==1.4)
Requires-Dist: intervals (==0.8.1)
Requires-Dist: isort (==4.3.4)
Requires-Dist: itsdangerous (==0.24)
Requires-Dist: Jinja2 (==2.10.1)
Requires-Dist: lazy-object-proxy (==1.3.1)
Requires-Dist: Mako (==1.0.7)
Requires-Dist: MarkupSafe (==1.0)
Requires-Dist: marshmallow (==2.15.3)
Requires-Dist: marshmallow-sqlalchemy (==0.14.0)
Requires-Dist: mccabe (==0.6.1)
Requires-Dist: psycopg2 (==2.7.5)
Requires-Dist: pycodestyle (==2.3.1)
Requires-Dist: pycparser (==2.18)
Requires-Dist: pyflakes (==1.6.0)
Requires-Dist: pylint (==2.0.1)
Requires-Dist: PyMySQL (==0.9.2)
Requires-Dist: python-dateutil (==2.7.3)
Requires-Dist: python-editor (==1.0.3)
Requires-Dist: redis (==2.10.6)
Requires-Dist: requests (>=2.20.0)
Requires-Dist: rope (==0.11.0)
Requires-Dist: six (==1.11.0)
Requires-Dist: SQLAlchemy (==1.3.3)
Requires-Dist: SQLAlchemy-Utils (==0.33.3)
Requires-Dist: typed-ast (==1.1.0)
Requires-Dist: urllib3 (==1.25)
Requires-Dist: validators (==0.12.2)
Requires-Dist: Werkzeug (==0.14.1)
Requires-Dist: wrapt (==1.10.11)
Requires-Dist: WTForms (==2.2.1)
Requires-Dist: WTForms-Alchemy (==0.16.7)
Requires-Dist: WTForms-Components (==0.10.3)
Requires-Dist: bcrypt (==3.1.4)
Requires-Dist: uWSGI (==2.0.18)
Requires-Dist: sqlparse (==0.3.0)
Requires-Dist: impyla (==0.14.1)
